molpred/__init__.py
molpred/decorators.py
molpred/experiment.py
molpred/plot.py
molpred/version.py
molpred/data/__init__.py
molpred/data/column_specifier.py
molpred/data/common.py
molpred/data/features_and_targets.py
molpred/data/inchi_loader.py
molpred/data/train_test_split.py
molpred/model/__init__.py
molpred/model/base.py
molpred/model/scoring.py
molpred-2023.7.dist-info/METADATA
molpred-2023.7.dist-info/WHEEL
molpred-2023.7.dist-info/licenses/LICENSE.txt
molpred-2023.7.dist-info/RECORD
