Metadata-Version: 2.1
Name: molpred
Version: 2023.7
Summary: A framework for building machine- and deep-learning predictors for molecular characteristics using Hydronaut and Chemfeat.
Project-URL: homepage, https://gitlab.inria.fr/jrye/molpred
Project-URL: repository, https://gitlab.inria.fr/jrye/molpred.git
Project-URL: documentation, https://jrye.gitlabpages.inria.fr/molpred
Project-URL: issues, https://gitlab.inria.fr/jrye/molpred/-/issues
Author-email: Jan-Michael Rye <jan-michael.rye@inria.fr>
License: MIT License
License-File: LICENSE.txt
Classifier: Operating System :: OS Independent
Classifier: Programming Language :: Python :: 3
Requires-Python: >=3.7
Requires-Dist: chemfeat
Requires-Dist: hydronaut
Requires-Dist: matplotlib
Requires-Dist: numpy
Requires-Dist: pandas
Requires-Dist: scikit-learn
Requires-Dist: seaborn
Requires-Dist: simple-file-lock
